<annotation>
        <folder>FOLDER</folder>
        <filename>079332906.jpg</filename>
        <path>data/scenes/train\079332906.jpg</path>
        <source>
                <database>Unknown</database>
        </source>
        <size>
                <width>720</width>
                <height>720</height>
                <depth>3</depth>
        </size>
 <object>
                <name>7h</name>
                <pose>Unspecified</pose>
                <truncated>0</truncated>
                <difficult>0</difficult>
                <bndbox>
                        <xmin>261</xmin>
                        <ymin>237</ymin>
                        <xmax>290</xmax>
                        <ymax>288</ymax>
                </bndbox>
        </object>
 <object>
                <name>Qc</name>
                <pose>Unspecified</pose>
                <truncated>0</truncated>
                <difficult>0</difficult>
                <bndbox>
                        <xmin>289</xmin>
                        <ymin>260</ymin>
                        <xmax>327</xmax>
                        <ymax>313</ymax>
                </bndbox>
        </object>
 <object>
                <name>Js</name>
                <pose>Unspecified</pose>
                <truncated>0</truncated>
                <difficult>0</difficult>
                <bndbox>
                        <xmin>324</xmin>
                        <ymin>295</ymin>
                        <xmax>370</xmax>
                        <ymax>345</ymax>
                </bndbox>
        </object>
 <object>
                <name>Js</name>
                <pose>Unspecified</pose>
                <truncated>0</truncated>
                <difficult>0</difficult>
                <bndbox>
                        <xmin>302</xmin>
                        <ymin>482</ymin>
                        <xmax>347</xmax>
                        <ymax>534</ymax>
                </bndbox>
        </object>
</annotation>        
