<annotation>
        <folder>FOLDER</folder>
        <filename>240345218.jpg</filename>
        <path>data/scenes/train\240345218.jpg</path>
        <source>
                <database>Unknown</database>
        </source>
        <size>
                <width>720</width>
                <height>720</height>
                <depth>3</depth>
        </size>
 <object>
                <name>Jc</name>
                <pose>Unspecified</pose>
                <truncated>0</truncated>
                <difficult>0</difficult>
                <bndbox>
                        <xmin>336</xmin>
                        <ymin>582</ymin>
                        <xmax>397</xmax>
                        <ymax>661</ymax>
                </bndbox>
        </object>
 <object>
                <name>8s</name>
                <pose>Unspecified</pose>
                <truncated>0</truncated>
                <difficult>0</difficult>
                <bndbox>
                        <xmin>290</xmin>
                        <ymin>546</ymin>
                        <xmax>355</xmax>
                        <ymax>613</ymax>
                </bndbox>
        </object>
 <object>
                <name>9h</name>
                <pose>Unspecified</pose>
                <truncated>0</truncated>
                <difficult>0</difficult>
                <bndbox>
                        <xmin>247</xmin>
                        <ymin>494</ymin>
                        <xmax>317</xmax>
                        <ymax>547</ymax>
                </bndbox>
        </object>
 <object>
                <name>9h</name>
                <pose>Unspecified</pose>
                <truncated>0</truncated>
                <difficult>0</difficult>
                <bndbox>
                        <xmin>354</xmin>
                        <ymin>211</ymin>
                        <xmax>423</xmax>
                        <ymax>263</ymax>
                </bndbox>
        </object>
</annotation>        
