<annotation>
        <folder>FOLDER</folder>
        <filename>372967858.jpg</filename>
        <path>data/scenes/train\372967858.jpg</path>
        <source>
                <database>Unknown</database>
        </source>
        <size>
                <width>720</width>
                <height>720</height>
                <depth>3</depth>
        </size>
 <object>
                <name>5s</name>
                <pose>Unspecified</pose>
                <truncated>0</truncated>
                <difficult>0</difficult>
                <bndbox>
                        <xmin>555</xmin>
                        <ymin>523</ymin>
                        <xmax>579</xmax>
                        <ymax>576</ymax>
                </bndbox>
        </object>
 <object>
                <name>5s</name>
                <pose>Unspecified</pose>
                <truncated>0</truncated>
                <difficult>0</difficult>
                <bndbox>
                        <xmin>458</xmin>
                        <ymin>353</ymin>
                        <xmax>482</xmax>
                        <ymax>408</ymax>
                </bndbox>
        </object>
 <object>
                <name>Js</name>
                <pose>Unspecified</pose>
                <truncated>0</truncated>
                <difficult>0</difficult>
                <bndbox>
                        <xmin>112</xmin>
                        <ymin>37</ymin>
                        <xmax>159</xmax>
                        <ymax>118</ymax>
                </bndbox>
        </object>
 <object>
                <name>Js</name>
                <pose>Unspecified</pose>
                <truncated>0</truncated>
                <difficult>0</difficult>
                <bndbox>
                        <xmin>210</xmin>
                        <ymin>312</ymin>
                        <xmax>256</xmax>
                        <ymax>398</ymax>
                </bndbox>
        </object>
</annotation>        
