<annotation>
        <folder>FOLDER</folder>
        <filename>864316502.jpg</filename>
        <path>data/scenes/train\864316502.jpg</path>
        <source>
                <database>Unknown</database>
        </source>
        <size>
                <width>720</width>
                <height>720</height>
                <depth>3</depth>
        </size>
 <object>
                <name>7s</name>
                <pose>Unspecified</pose>
                <truncated>0</truncated>
                <difficult>0</difficult>
                <bndbox>
                        <xmin>413</xmin>
                        <ymin>467</ymin>
                        <xmax>479</xmax>
                        <ymax>534</ymax>
                </bndbox>
        </object>
 <object>
                <name>Kh</name>
                <pose>Unspecified</pose>
                <truncated>0</truncated>
                <difficult>0</difficult>
                <bndbox>
                        <xmin>350</xmin>
                        <ymin>497</ymin>
                        <xmax>417</xmax>
                        <ymax>573</ymax>
                </bndbox>
        </object>
 <object>
                <name>3h</name>
                <pose>Unspecified</pose>
                <truncated>0</truncated>
                <difficult>0</difficult>
                <bndbox>
                        <xmin>295</xmin>
                        <ymin>517</ymin>
                        <xmax>341</xmax>
                        <ymax>596</ymax>
                </bndbox>
        </object>
 <object>
                <name>3h</name>
                <pose>Unspecified</pose>
                <truncated>0</truncated>
                <difficult>0</difficult>
                <bndbox>
                        <xmin>48</xmin>
                        <ymin>341</ymin>
                        <xmax>92</xmax>
                        <ymax>418</ymax>
                </bndbox>
        </object>
</annotation>        
